README.md
setup.py
venv/__init__.py
venv/lib/__init__.py
vintool/__init__.py
vintool/env.py
vintool/http.py
vintool/mq.py
vintool/oss.py
vintool/rabbit_mq.py
vintool/singleton.py
vintool/video.py
vintool.egg-info/.gitkeep
vintool.egg-info/PKG-INFO
vintool.egg-info/SOURCES.txt
vintool.egg-info/dependency_links.txt
vintool.egg-info/requires.txt
vintool.egg-info/top_level.txt
vintool/exception/__init__.py