Metadata-Version: 2.1
Name: vintool
Version: 1.1.3
Summary: tools
Home-page: https://github.com/fengmm521/pipProject
Author: vincent
Author-email: long_ty@163.com
License: MIT Licence
Keywords: tools
Platform: any
Requires-Python: >=3.6
